rs_document-0.1.8.dist-info/METADATA
rs_document-0.1.8.dist-info/WHEEL
rs_document-0.1.8.dist-info/licenses/LICENSE.md
rs_document/__init__.py
rs_document/post_processors.py
rs_document/py.typed
rs_document/rs_document.cpython-313-aarch64-linux-gnu.so
rs_document/rs_document.pyi
rs_document-0.1.8.dist-info/RECORD
