Metadata-Version: 2.4
Name: rs_document
Version: 0.1.8
Classifier: Development Status :: 3 - Alpha
Classifier: Programming Language :: Rust
Classifier: Programming Language :: Python :: Implementation :: CPython
Classifier: Programming Language :: Python :: Implementation :: PyPy
Classifier: Programming Language :: Python :: 3
Classifier: Programming Language :: Python :: 3.10
Classifier: Programming Language :: Python :: 3.11
Classifier: Programming Language :: Python :: 3.12
Classifier: Programming Language :: Python :: 3.13
Classifier: Intended Audience :: Developers
Classifier: Intended Audience :: Science/Research
Classifier: License :: OSI Approved :: MIT License
Classifier: Natural Language :: English
Classifier: Topic :: Scientific/Engineering :: Artificial Intelligence
Classifier: Topic :: Text Processing
Classifier: Topic :: Text Processing :: Filters
Classifier: Topic :: Software Development :: Libraries :: Python Modules
Requires-Dist: pytest>=7.0.0 ; extra == 'test'
Requires-Dist: pytest-cov>=4.0.0 ; extra == 'test'
Requires-Dist: langchain-text-splitters>=0.0.1 ; extra == 'test'
Requires-Dist: hypothesis>=6.148.1 ; extra == 'test'
Requires-Dist: pytest>=7.0.0 ; extra == 'dev'
Requires-Dist: pytest-cov>=4.0.0 ; extra == 'dev'
Requires-Dist: langchain-text-splitters>=0.0.1 ; extra == 'dev'
Requires-Dist: ruff>=0.1.0 ; extra == 'dev'
Requires-Dist: nox>=2023.4.0 ; extra == 'dev'
Requires-Dist: prek>=0.2.0 ; extra == 'dev'
Provides-Extra: test
Provides-Extra: dev
License-File: LICENSE.md
Summary: High-performance Rust implementation of LangChain's Document model and Unstructured.io's text cleaners for RAG applications
Keywords: LangChain,Document,cleanup,splitter,rust,maturin,pyo3,RAG,Unstructured,text-processing,performance,parallel
Author-email: Cam Barts <cam@coder.cam>
Requires-Python: >=3.10
Project-URL: homepage, https://github.com/cam-barts/rs_document
Project-URL: documentation, https://cam-barts.github.io/rs_document
Project-URL: repository, https://github.com/cam-barts/rs_document
Project-URL: changelog, https://github.com/cam-barts/rs_document/blob/main/CHANGELOG.md
Project-URL: Issue Tracker, https://github.com/cam-barts/rs_document/issues
